sco_datastore-0.9.0.dist-info/DESCRIPTION.rst
sco_datastore-0.9.0.dist-info/METADATA
sco_datastore-0.9.0.dist-info/RECORD
sco_datastore-0.9.0.dist-info/WHEEL
sco_datastore-0.9.0.dist-info/metadata.json
sco_datastore-0.9.0.dist-info/top_level.txt
scodata/__init__.py
scodata/api.py
scodata/attribute.py
scodata/datastore.py
scodata/experiment.py
scodata/funcdata.py
scodata/image.py
scodata/modelrun.py
scodata/mongo.py
scodata/prediction.py
scodata/subject.py
scodata/upload_images.py
scodata/upload_subject.py
