Metadata-Version: 2.0
Name: sco-datastore
Version: 0.9.0
Summary: Library to manipulate objects in the Standard Cortical Observer Data Store
Home-page: https://github.com/heikomuller/sco-datastore
Author: Heiko Mueller
Author-email: heiko.muller@gmail.com
License: GPLv3
Keywords: neuroscience vision cortex
Platform: UNKNOWN
Requires-Dist: pymongo
